financial_canvas/__init__.py
financial_canvas/indicators_glyphs.py
financial_canvas/figures/Candlestick.py
financial_canvas/figures/CustomFigure.py
financial_canvas/figures/FilteringDateRangeSlider.py
financial_canvas/figures/Line.py
financial_canvas/figures/MultiCircle.py
financial_canvas/figures/PreviewSlider.py
financial_canvas/figures/__init__.py
financial_canvas/figures/constants.py
financial_canvas/figures/utils.py
financial_canvas/js_callbacks/__init__.py
financial_canvas/js_callbacks/update_render_range.js
financial_canvas/js_callbacks/y_axis_auto_range.js
financial_canvas-1.4.2.dist-info/LICENSE
financial_canvas-1.4.2.dist-info/METADATA
financial_canvas-1.4.2.dist-info/WHEEL
financial_canvas-1.4.2.dist-info/top_level.txt
financial_canvas-1.4.2.dist-info/RECORD
