Metadata-Version: 2.1
Name: financial-canvas
Version: 1.4.2
Summary: Draw interactive candlesticks on browser canvas from Python.
Home-page: UNKNOWN
Author: Evgeniia Vakarina
Author-email: 27793901+EvgeniiaVak@users.noreply.github.com
License: UNKNOWN
Platform: UNKNOWN
Classifier: Programming Language :: Python :: 3
Classifier: License :: OSI Approved :: MIT License
Classifier: Operating System :: OS Independent
Requires-Python: >=3.7
License-File: LICENSE
Requires-Dist: bokeh
Requires-Dist: pandas
Requires-Dist: seaborn
Requires-Dist: yapf (==0.31.0)
